README
setup.py
berend/__init__.py
berend/api.py
berend/config.py
berend/noapi.py
berend.egg-info/PKG-INFO
berend.egg-info/SOURCES.txt
berend.egg-info/dependency_links.txt
berend.egg-info/entry_points.txt
berend.egg-info/requires.txt
berend.egg-info/top_level.txt
berend/plugins/__init__.py
berend/plugins/die.py
berend/plugins/help.py
berend/plugins/ping.py