Metadata-Version: 1.1
Name: berend
Version: 0.4
Summary: Extensible IRC bot
Home-page: https://github.com/ronaldevers/berend
Author: Ronald Evers
Author-email: ronald@ch10.nl
License: UNKNOWN
Platform: UNKNOWN
Classifier: License :: Public Domain
Classifier: Programming Language :: Python :: 2.7
